pelican/plugins/math_svg/__init__.py
pelican/plugins/math_svg/database.py
pelican/plugins/math_svg/extension.py
pelican/plugins/math_svg/main.py
pelican/plugins/math_svg/markdown_extension.py
pelican/plugins/math_svg/math_svg.py
pelican/plugins/math_svg/math_svg_test.py
pelican/plugins/math_svg/render.py
pelican/plugins/math_svg/settings.py
pelican/plugins/math_svg/svgo.js
pelican_math_svg-0.10.5.dist-info/LICENSE
pelican_math_svg-0.10.5.dist-info/METADATA
pelican_math_svg-0.10.5.dist-info/WHEEL
pelican_math_svg-0.10.5.dist-info/entry_points.txt
pelican_math_svg-0.10.5.dist-info/RECORD
