Metadata-Version: 2.1
Name: pelican-math-svg
Version: 0.10.5
Summary: Render math expressions to svg and embed them.
Home-page: https://github.com/f-koehler/pelican-math-svg
License: AGPL-3.0
Keywords: pelican,plugin
Author: Fabian Köhler
Author-email: fabian.koehler@protonmail.ch
Requires-Python: >=3.10,<4.0
Classifier: Development Status :: 5 - Production/Stable
Classifier: Environment :: Console
Classifier: Framework :: Pelican
Classifier: Framework :: Pelican :: Plugins
Classifier: Intended Audience :: End Users/Desktop
Classifier: License :: OSI Approved :: GNU Affero General Public License v3
Classifier: Operating System :: OS Independent
Classifier: Programming Language :: Python :: 3
Classifier: Programming Language :: Python :: 3.10
Classifier: Programming Language :: Python :: 3.11
Classifier: Topic :: Internet :: WWW/HTTP
Classifier: Topic :: Software Development :: Libraries :: Python Modules
Provides-Extra: markdown
Requires-Dist: lxml (>=4.6.3,<5.0.0)
Requires-Dist: markdown (>=3.2.2,<4.0.0) ; extra == "markdown"
Requires-Dist: pelican (>=4.5,<5.0)
Requires-Dist: setuptools (>=68.0.0,<69.0.0)
Requires-Dist: typer (>=0.9.0,<0.10.0)
Project-URL: Documentation, https://docs.getpelican.com
Project-URL: Funding, https://donate.getpelican.com/
Project-URL: Issue Tracker, https://github.com/f-koehler/pelican-math-svg/issues
Project-URL: Repository, https://github.com/f-koehler/pelican-math-svg
